tensarflaw/__init__.py
tensarflaw/__main__.py
tensarflaw/load.py
tensarflaw-0.1.1.dist-info/licenses/LICENSE
tensarflaw-0.1.1.dist-info/METADATA
tensarflaw-0.1.1.dist-info/WHEEL
tensarflaw-0.1.1.dist-info/entry_points.txt
tensarflaw-0.1.1.dist-info/top_level.txt
tensarflaw-0.1.1.dist-info/RECORD
